snarled/__init__.py
snarled/__main__.py
snarled/main.py
snarled/trace.py
snarled/types.py
snarled/utils.py
snarled-1.0.dist-info/METADATA
snarled-1.0.dist-info/WHEEL
snarled-1.0.dist-info/entry_points.txt
snarled-1.0.dist-info/licenses/LICENSE.md
snarled-1.0.dist-info/RECORD
