Metadata-Version: 2.1
Name: snarled
Version: 1.0
Summary: CAD layout electrical connectivity checker
Author-email: Jan Petykiewicz <jan@mpxd.net>
License: GNU General Public License
License-File: LICENSE.md
Keywords: CAD,EDA,IC,checking,connectivity,design,drawing,electronics,label,layout,lvs,mask,pattern,photonics,schematic,short,unintentional,verification
Classifier: Development Status :: 4 - Beta
Classifier: Intended Audience :: Developers
Classifier: Intended Audience :: Information Technology
Classifier: Intended Audience :: Manufacturing
Classifier: Intended Audience :: Science/Research
Classifier: License :: OSI Approved :: GNU General Public License v3 (GPLv3)
Classifier: Programming Language :: Python :: 3
Classifier: Topic :: Scientific/Engineering :: Electronic Design Automation (EDA)
Requires-Python: >=3.10
Requires-Dist: klayout~=0.28
